streamsx/elasticsearch/__init__.py
streamsx/elasticsearch/_elasticsearch.py
streamsx.elasticsearch-1.3.4.dist-info/LICENSE.txt
streamsx.elasticsearch-1.3.4.dist-info/METADATA
streamsx.elasticsearch-1.3.4.dist-info/WHEEL
streamsx.elasticsearch-1.3.4.dist-info/top_level.txt
streamsx.elasticsearch-1.3.4.dist-info/RECORD
